{
  "station": "Rīgā",
  "date": "2026-04-28",
  "updated_utc": "2026-04-28T16:58:07Z",
  "updated": "28.04.2026 19:58:07",
  "total": 153,
  "trains": [
    {
      "nr": "6871",
      "dest": "Jelgava",
      "dep_utc": "2026-04-28T05:04:00Z",
      "fuel": "E",
      "route_id": "763811",
      "track": 1,
      "platform": 2
    },
    {
      "nr": "6202",
      "dest": "Aizkraukle",
      "dep_utc": "2026-04-28T05:09:00Z",
      "fuel": "E",
      "route_id": "763812",
      "track": 4,
      "platform": 3
    },
    {
      "nr": "6301",
      "dest": "Imanta",
      "dep_utc": "2026-04-28T05:15:00Z",
      "fuel": "E",
      "route_id": "763814",
      "track": 3,
      "platform": 3
    },
    {
      "nr": "6501",
      "dest": "Tukums 1",
      "dep_utc": "2026-04-28T05:30:00Z",
      "fuel": "E",
      "route_id": "763815",
      "track": 3,
      "platform": 3
    },
    {
      "nr": "6701",
      "dest": "Jelgava",
      "dep_utc": "2026-04-28T05:35:00Z",
      "fuel": "E",
      "route_id": "763816",
      "track": 1,
      "platform": 2
    },
    {
      "nr": "6204",
      "dest": "Ogre",
      "dep_utc": "2026-04-28T05:39:00Z",
      "fuel": "E",
      "route_id": "763818",
      "track": 4,
      "platform": 3
    },
    {
      "nr": "6102",
      "dest": "Skulte",
      "dep_utc": "2026-04-28T05:45:00Z",
      "fuel": "E",
      "route_id": "763821",
      "track": 10,
      "platform": 2
    },
    {
      "nr": "6303",
      "dest": "Zolitūde",
      "dep_utc": "2026-04-28T06:00:00Z",
      "fuel": "E",
      "route_id": "763827",
      "track": 3,
      "platform": 3
    },
    {
      "nr": "6873",
      "dest": "Jelgava",
      "dep_utc": "2026-04-28T06:04:00Z",
      "fuel": "E",
      "route_id": "763830",
      "track": 1,
      "platform": 2
    },
    {
      "nr": "6206",
      "dest": "Aizkraukle",
      "dep_utc": "2026-04-28T06:09:00Z",
      "fuel": "E",
      "route_id": "763833",
      "track": 4,
      "platform": 3
    },
    {
      "nr": "6104",
      "dest": "Saulkrasti",
      "dep_utc": "2026-04-28T06:15:00Z",
      "fuel": "E",
      "route_id": "763834",
      "track": 10,
      "platform": 2
    },
    {
      "nr": "6208",
      "dest": "Ogre",
      "dep_utc": "2026-04-28T06:24:00Z",
      "fuel": "E",
      "route_id": "763835",
      "track": 10,
      "platform": 2
    },
    {
      "nr": "6503",
      "dest": "Tukums 1",
      "dep_utc": "2026-04-28T06:30:00Z",
      "fuel": "E",
      "route_id": "763837",
      "track": 3,
      "platform": 3
    },
    {
      "nr": "862",
      "dest": "Valmiera",
      "dep_utc": "2026-04-28T06:30:00Z",
      "fuel": "D",
      "route_id": "763838",
      "track": 11,
      "platform": 1
    },
    {
      "nr": "6705",
      "dest": "Jelgava",
      "dep_utc": "2026-04-28T06:35:00Z",
      "fuel": "E",
      "route_id": "763839",
      "track": 5,
      "platform": 4
    },
    {
      "nr": "6210",
      "dest": "Lielvārde",
      "dep_utc": "2026-04-28T06:39:00Z",
      "fuel": "E",
      "route_id": "763840",
      "track": 4,
      "platform": 3
    },
    {
      "nr": "6106",
      "dest": "Skulte",
      "dep_utc": "2026-04-28T06:45:00Z",
      "fuel": "E",
      "route_id": "763843",
      "track": 10,
      "platform": 2
    },
    {
      "nr": "6305",
      "dest": "Zolitūde",
      "dep_utc": "2026-04-28T07:00:00Z",
      "fuel": "E",
      "route_id": "763848",
      "track": 3,
      "platform": 3
    },
    {
      "nr": "802",
      "dest": "Daugavpils",
      "dep_utc": "2026-04-28T07:01:00Z",
      "fuel": "D",
      "route_id": "763851",
      "track": 10,
      "platform": 2
    },
    {
      "nr": "6875",
      "dest": "Jelgava",
      "dep_utc": "2026-04-28T07:04:00Z",
      "fuel": "E",
      "route_id": "763853",
      "track": 5,
      "platform": 4
    },
    {
      "nr": "6212",
      "dest": "Aizkraukle",
      "dep_utc": "2026-04-28T07:09:00Z",
      "fuel": "E",
      "route_id": "763856",
      "track": 4,
      "platform": 3
    },
    {
      "nr": "6108",
      "dest": "Saulkrasti",
      "dep_utc": "2026-04-28T07:15:00Z",
      "fuel": "E",
      "route_id": "763857",
      "track": 1,
      "platform": 2
    },
    {
      "nr": "6505",
      "dest": "Tukums 1",
      "dep_utc": "2026-04-28T07:30:00Z",
      "fuel": "E",
      "route_id": "763860",
      "track": 3,
      "platform": 3
    },
    {
      "nr": "6709",
      "dest": "Jelgava",
      "dep_utc": "2026-04-28T07:35:00Z",
      "fuel": "E",
      "route_id": "763862",
      "track": 5,
      "platform": 4
    },
    {
      "nr": "6214",
      "dest": "Lielvārde",
      "dep_utc": "2026-04-28T07:39:00Z",
      "fuel": "E",
      "route_id": "763864",
      "track": 4,
      "platform": 3
    },
    {
      "nr": "6110",
      "dest": "Skulte",
      "dep_utc": "2026-04-28T07:45:00Z",
      "fuel": "E",
      "route_id": "763867",
      "track": 11,
      "platform": 1
    },
    {
      "nr": "6307",
      "dest": "Zolitūde",
      "dep_utc": "2026-04-28T08:00:00Z",
      "fuel": "E",
      "route_id": "763872",
      "track": 3,
      "platform": 3
    },
    {
      "nr": "830",
      "dest": "Sigulda",
      "dep_utc": "2026-04-28T08:00:00Z",
      "fuel": "D",
      "route_id": "763874",
      "track": 12,
      "platform": 1
    },
    {
      "nr": "804",
      "dest": "Zilupe",
      "dep_utc": "2026-04-28T08:01:00Z",
      "fuel": "D",
      "route_id": "763875",
      "track": 1,
      "platform": 2
    },
    {
      "nr": "6877",
      "dest": "Jelgava",
      "dep_utc": "2026-04-28T08:04:00Z",
      "fuel": "E",
      "route_id": "763877",
      "track": 5,
      "platform": 4
    },
    {
      "nr": "6216",
      "dest": "Lielvārde",
      "dep_utc": "2026-04-28T08:09:00Z",
      "fuel": "E",
      "route_id": "763880",
      "track": 4,
      "platform": 3
    },
    {
      "nr": "6112",
      "dest": "Carnikava",
      "dep_utc": "2026-04-28T08:15:00Z",
      "fuel": "E",
      "route_id": "763881",
      "track": 11,
      "platform": 1
    },
    {
      "nr": "6507",
      "dest": "Tukums 1",
      "dep_utc": "2026-04-28T08:30:00Z",
      "fuel": "E",
      "route_id": "763882",
      "track": 3,
      "platform": 3
    },
    {
      "nr": "6713",
      "dest": "Jelgava",
      "dep_utc": "2026-04-28T08:35:00Z",
      "fuel": "E",
      "route_id": "763883",
      "track": 5,
      "platform": 4
    },
    {
      "nr": "6218",
      "dest": "Aizkraukle",
      "dep_utc": "2026-04-28T08:39:00Z",
      "fuel": "E",
      "route_id": "763885",
      "track": 4,
      "platform": 3
    },
    {
      "nr": "6114",
      "dest": "Skulte",
      "dep_utc": "2026-04-28T08:45:00Z",
      "fuel": "E",
      "route_id": "763886",
      "track": 11,
      "platform": 1
    },
    {
      "nr": "6309",
      "dest": "Zolitūde",
      "dep_utc": "2026-04-28T09:00:00Z",
      "fuel": "E",
      "route_id": "763892",
      "track": 3,
      "platform": 3
    },
    {
      "nr": "6220",
      "dest": "Ogre",
      "dep_utc": "2026-04-28T09:09:00Z",
      "fuel": "E",
      "route_id": "763896",
      "track": 4,
      "platform": 3
    },
    {
      "nr": "832",
      "dest": "Sigulda",
      "dep_utc": "2026-04-28T09:30:00Z",
      "fuel": "D",
      "route_id": "763899",
      "track": 12,
      "platform": 1
    },
    {
      "nr": "6509",
      "dest": "Tukums 1",
      "dep_utc": "2026-04-28T09:30:00Z",
      "fuel": "E",
      "route_id": "763900",
      "track": 3,
      "platform": 3
    },
    {
      "nr": "6715",
      "dest": "Jelgava",
      "dep_utc": "2026-04-28T09:35:00Z",
      "fuel": "E",
      "route_id": "763902",
      "track": 5,
      "platform": 4
    },
    {
      "nr": "6222",
      "dest": "Aizkraukle",
      "dep_utc": "2026-04-28T09:39:00Z",
      "fuel": "E",
      "route_id": "763903",
      "track": 4,
      "platform": 3
    },
    {
      "nr": "6118",
      "dest": "Saulkrasti",
      "dep_utc": "2026-04-28T09:45:00Z",
      "fuel": "E",
      "route_id": "763906",
      "track": 11,
      "platform": 1
    },
    {
      "nr": "6311",
      "dest": "Zolitūde",
      "dep_utc": "2026-04-28T10:00:00Z",
      "fuel": "E",
      "route_id": "763909",
      "track": 3,
      "platform": 3
    },
    {
      "nr": "702",
      "dest": "Daugavpils",
      "dep_utc": "2026-04-28T10:01:00Z",
      "fuel": "D",
      "route_id": "763911",
      "track": 11,
      "platform": 1
    },
    {
      "nr": "6511",
      "dest": "Tukums 1",
      "dep_utc": "2026-04-28T10:30:00Z",
      "fuel": "E",
      "route_id": "763916",
      "track": 3,
      "platform": 3
    },
    {
      "nr": "6717",
      "dest": "Jelgava",
      "dep_utc": "2026-04-28T10:35:00Z",
      "fuel": "E",
      "route_id": "763918",
      "track": 5,
      "platform": 4
    },
    {
      "nr": "6224",
      "dest": "Lielvārde",
      "dep_utc": "2026-04-28T10:39:00Z",
      "fuel": "E",
      "route_id": "763920",
      "track": 4,
      "platform": 3
    },
    {
      "nr": "6122",
      "dest": "Skulte",
      "dep_utc": "2026-04-28T10:45:00Z",
      "fuel": "E",
      "route_id": "763921",
      "track": 10,
      "platform": 2
    },
    {
      "nr": "6313",
      "dest": "Zolitūde",
      "dep_utc": "2026-04-28T11:00:00Z",
      "fuel": "E",
      "route_id": "763926",
      "track": 3,
      "platform": 3
    },
    {
      "nr": "6513",
      "dest": "Tukums 1",
      "dep_utc": "2026-04-28T11:30:00Z",
      "fuel": "E",
      "route_id": "763930",
      "track": 3,
      "platform": 3
    },
    {
      "nr": "6719",
      "dest": "Jelgava",
      "dep_utc": "2026-04-28T11:35:00Z",
      "fuel": "E",
      "route_id": "763931",
      "track": 5,
      "platform": 4
    },
    {
      "nr": "6126",
      "dest": "Saulkrasti",
      "dep_utc": "2026-04-28T11:38:00Z",
      "fuel": "E",
      "route_id": "763932",
      "track": 10,
      "platform": 2
    },
    {
      "nr": "6226",
      "dest": "Aizkraukle",
      "dep_utc": "2026-04-28T11:39:00Z",
      "fuel": "E",
      "route_id": "763933",
      "track": 4,
      "platform": 3
    },
    {
      "nr": "874",
      "dest": "Valga",
      "dep_utc": "2026-04-28T11:45:00Z",
      "fuel": "D",
      "route_id": "763935",
      "track": 1,
      "platform": 2
    },
    {
      "nr": "6315",
      "dest": "Zolitūde",
      "dep_utc": "2026-04-28T12:00:00Z",
      "fuel": "E",
      "route_id": "763939",
      "track": 3,
      "platform": 3
    },
    {
      "nr": "704",
      "dest": "Ludza",
      "dep_utc": "2026-04-28T12:01:00Z",
      "fuel": "D",
      "route_id": "763941",
      "track": 11,
      "platform": 1
    },
    {
      "nr": "6515",
      "dest": "Tukums 1",
      "dep_utc": "2026-04-28T12:30:00Z",
      "fuel": "E",
      "route_id": "763943",
      "track": 3,
      "platform": 3
    },
    {
      "nr": "836",
      "dest": "Sigulda",
      "dep_utc": "2026-04-28T12:30:00Z",
      "fuel": "D",
      "route_id": "763944",
      "track": 12,
      "platform": 1
    },
    {
      "nr": "810",
      "dest": "Daugavpils",
      "dep_utc": "2026-04-28T12:31:00Z",
      "fuel": "D",
      "route_id": "763945",
      "track": 1,
      "platform": 2
    },
    {
      "nr": "6721",
      "dest": "Jelgava",
      "dep_utc": "2026-04-28T12:35:00Z",
      "fuel": "E",
      "route_id": "763947",
      "track": 5,
      "platform": 4
    },
    {
      "nr": "6228",
      "dest": "Aizkraukle",
      "dep_utc": "2026-04-28T12:39:00Z",
      "fuel": "E",
      "route_id": "763948",
      "track": 4,
      "platform": 3
    },
    {
      "nr": "6130",
      "dest": "Skulte",
      "dep_utc": "2026-04-28T12:45:00Z",
      "fuel": "E",
      "route_id": "763950",
      "track": 11,
      "platform": 1
    },
    {
      "nr": "6317",
      "dest": "Zolitūde",
      "dep_utc": "2026-04-28T13:00:00Z",
      "fuel": "E",
      "route_id": "763955",
      "track": 3,
      "platform": 3
    },
    {
      "nr": "6230",
      "dest": "Ogre",
      "dep_utc": "2026-04-28T13:09:00Z",
      "fuel": "E",
      "route_id": "763958",
      "track": 4,
      "platform": 3
    },
    {
      "nr": "6517",
      "dest": "Tukums 1",
      "dep_utc": "2026-04-28T13:30:00Z",
      "fuel": "E",
      "route_id": "763962",
      "track": 3,
      "platform": 3
    },
    {
      "nr": "6723",
      "dest": "Jelgava",
      "dep_utc": "2026-04-28T13:35:00Z",
      "fuel": "E",
      "route_id": "763964",
      "track": 5,
      "platform": 4
    },
    {
      "nr": "6232",
      "dest": "Aizkraukle",
      "dep_utc": "2026-04-28T13:39:00Z",
      "fuel": "E",
      "route_id": "763965",
      "track": 4,
      "platform": 3
    },
    {
      "nr": "6134",
      "dest": "Saulkrasti",
      "dep_utc": "2026-04-28T13:45:00Z",
      "fuel": "E",
      "route_id": "763968",
      "track": 10,
      "platform": 2
    },
    {
      "nr": "6319",
      "dest": "Zolitūde",
      "dep_utc": "2026-04-28T14:00:00Z",
      "fuel": "E",
      "route_id": "763972",
      "track": 3,
      "platform": 3
    },
    {
      "nr": "6234",
      "dest": "Lielvārde",
      "dep_utc": "2026-04-28T14:09:00Z",
      "fuel": "E",
      "route_id": "763974",
      "track": 4,
      "platform": 3
    },
    {
      "nr": "6519",
      "dest": "Tukums 1",
      "dep_utc": "2026-04-28T14:30:00Z",
      "fuel": "E",
      "route_id": "763977",
      "track": 3,
      "platform": 3
    },
    {
      "nr": "838",
      "dest": "Sigulda",
      "dep_utc": "2026-04-28T14:30:00Z",
      "fuel": "D",
      "route_id": "763978",
      "track": 1,
      "platform": 2
    },
    {
      "nr": "6725",
      "dest": "Jelgava",
      "dep_utc": "2026-04-28T14:35:00Z",
      "fuel": "E",
      "route_id": "763980",
      "track": 5,
      "platform": 4
    },
    {
      "nr": "6236",
      "dest": "Aizkraukle",
      "dep_utc": "2026-04-28T14:39:00Z",
      "fuel": "E",
      "route_id": "763981",
      "track": 4,
      "platform": 3
    },
    {
      "nr": "6138",
      "dest": "Skulte",
      "dep_utc": "2026-04-28T14:45:00Z",
      "fuel": "E",
      "route_id": "763985",
      "track": 10,
      "platform": 2
    },
    {
      "nr": "6321",
      "dest": "Zolitūde",
      "dep_utc": "2026-04-28T15:00:00Z",
      "fuel": "E",
      "route_id": "763989",
      "track": 3,
      "platform": 3
    },
    {
      "nr": "6238",
      "dest": "Lielvārde",
      "dep_utc": "2026-04-28T15:09:00Z",
      "fuel": "E",
      "route_id": "763991",
      "track": 4,
      "platform": 3
    },
    {
      "nr": "6140",
      "dest": "Carnikava",
      "dep_utc": "2026-04-28T15:15:00Z",
      "fuel": "E",
      "route_id": "763992",
      "track": 1,
      "platform": 2
    },
    {
      "nr": "840",
      "dest": "Cēsis",
      "dep_utc": "2026-04-28T15:23:00Z",
      "fuel": "D",
      "route_id": "763994",
      "track": 11,
      "platform": 1
    },
    {
      "nr": "6521",
      "dest": "Tukums 1",
      "dep_utc": "2026-04-28T15:30:00Z",
      "fuel": "E",
      "route_id": "763996",
      "track": 3,
      "platform": 3
    },
    {
      "nr": "6729",
      "dest": "Jelgava",
      "dep_utc": "2026-04-28T15:35:00Z",
      "fuel": "E",
      "route_id": "763997",
      "track": 5,
      "platform": 4
    },
    {
      "nr": "6240",
      "dest": "Aizkraukle",
      "dep_utc": "2026-04-28T15:39:00Z",
      "fuel": "E",
      "route_id": "763999",
      "track": 4,
      "platform": 3
    },
    {
      "nr": "6142",
      "dest": "Skulte",
      "dep_utc": "2026-04-28T15:45:00Z",
      "fuel": "E",
      "route_id": "764001",
      "track": 10,
      "platform": 2
    },
    {
      "nr": "6323",
      "dest": "Zolitūde",
      "dep_utc": "2026-04-28T16:00:00Z",
      "fuel": "E",
      "route_id": "764004",
      "track": 3,
      "platform": 3
    },
    {
      "nr": "6879",
      "dest": "Jelgava",
      "dep_utc": "2026-04-28T16:05:00Z",
      "fuel": "E",
      "route_id": "764006",
      "track": 1,
      "platform": 2
    },
    {
      "nr": "842",
      "dest": "Sigulda",
      "dep_utc": "2026-04-28T16:05:00Z",
      "fuel": "D",
      "route_id": "764007",
      "track": 12,
      "platform": 1
    },
    {
      "nr": "6242",
      "dest": "Lielvārde",
      "dep_utc": "2026-04-28T16:09:00Z",
      "fuel": "E",
      "route_id": "764010",
      "track": 4,
      "platform": 3
    },
    {
      "nr": "6144",
      "dest": "Carnikava",
      "dep_utc": "2026-04-28T16:15:00Z",
      "fuel": "E",
      "route_id": "764012",
      "track": 11,
      "platform": 1
    },
    {
      "nr": "6523",
      "dest": "Tukums 1",
      "dep_utc": "2026-04-28T16:30:00Z",
      "fuel": "E",
      "route_id": "764015",
      "track": 3,
      "platform": 3
    },
    {
      "nr": "706",
      "dest": "Krāslava",
      "dep_utc": "2026-04-28T16:31:00Z",
      "fuel": "D",
      "route_id": "764016",
      "track": 1,
      "platform": 2
    },
    {
      "nr": "6733",
      "dest": "Jelgava",
      "dep_utc": "2026-04-28T16:35:00Z",
      "fuel": "E",
      "route_id": "764018",
      "track": 5,
      "platform": 4
    },
    {
      "nr": "6244",
      "dest": "Aizkraukle",
      "dep_utc": "2026-04-28T16:39:00Z",
      "fuel": "E",
      "route_id": "764019",
      "track": 4,
      "platform": 3
    },
    {
      "nr": "6146",
      "dest": "Skulte",
      "dep_utc": "2026-04-28T16:45:00Z",
      "fuel": "E",
      "route_id": "764021",
      "track": 10,
      "platform": 2
    },
    {
      "nr": "6325",
      "dest": "Zolitūde",
      "dep_utc": "2026-04-28T17:00:00Z",
      "fuel": "E",
      "route_id": "764026",
      "track": 3,
      "platform": 3
    },
    {
      "nr": "812",
      "dest": "Zilupe",
      "dep_utc": "2026-04-28T17:01:00Z",
      "fuel": "D",
      "route_id": "764028",
      "track": 11,
      "platform": 1
    },
    {
      "nr": "6881",
      "dest": "Jelgava",
      "dep_utc": "2026-04-28T17:05:00Z",
      "fuel": "E",
      "route_id": "764029",
      "track": 1,
      "platform": 2
    },
    {
      "nr": "6246",
      "dest": "Lielvārde",
      "dep_utc": "2026-04-28T17:09:00Z",
      "fuel": "E",
      "route_id": "764032",
      "track": 4,
      "platform": 3
    },
    {
      "nr": "6148",
      "dest": "Saulkrasti",
      "dep_utc": "2026-04-28T17:15:00Z",
      "fuel": "E",
      "route_id": "764034",
      "track": 10,
      "platform": 2
    },
    {
      "nr": "6248",
      "dest": "Ogre",
      "dep_utc": "2026-04-28T17:24:00Z",
      "fuel": "E",
      "route_id": "764036",
      "track": 1,
      "platform": 2
    },
    {
      "nr": "864",
      "dest": "Valmiera",
      "dep_utc": "2026-04-28T17:26:00Z",
      "fuel": "D",
      "route_id": "764037",
      "track": 12,
      "platform": 1
    },
    {
      "nr": "6525",
      "dest": "Tukums 1",
      "dep_utc": "2026-04-28T17:30:00Z",
      "fuel": "E",
      "route_id": "764038",
      "track": 3,
      "platform": 3
    },
    {
      "nr": "6737",
      "dest": "Jelgava",
      "dep_utc": "2026-04-28T17:35:00Z",
      "fuel": "E",
      "route_id": "764041",
      "track": 5,
      "platform": 4
    },
    {
      "nr": "6250",
      "dest": "Aizkraukle",
      "dep_utc": "2026-04-28T17:39:00Z",
      "fuel": "E",
      "route_id": "764042",
      "track": 4,
      "platform": 3
    },
    {
      "nr": "6152",
      "dest": "Skulte",
      "dep_utc": "2026-04-28T17:45:00Z",
      "fuel": "E",
      "route_id": "764045",
      "track": 11,
      "platform": 1
    },
    {
      "nr": "844",
      "dest": "Sigulda",
      "dep_utc": "2026-04-28T18:00:00Z",
      "fuel": "D",
      "route_id": "764049",
      "track": 12,
      "platform": 1
    },
    {
      "nr": "6327",
      "dest": "Zolitūde",
      "dep_utc": "2026-04-28T18:00:00Z",
      "fuel": "E",
      "route_id": "764050",
      "track": 3,
      "platform": 3
    },
    {
      "nr": "814",
      "dest": "Daugavpils",
      "dep_utc": "2026-04-28T18:01:00Z",
      "fuel": "D",
      "route_id": "764052",
      "track": 10,
      "platform": 2
    },
    {
      "nr": "6883",
      "dest": "Jelgava",
      "dep_utc": "2026-04-28T18:05:00Z",
      "fuel": "E",
      "route_id": "764054",
      "track": 5,
      "platform": 4
    },
    {
      "nr": "6252",
      "dest": "Lielvārde",
      "dep_utc": "2026-04-28T18:09:00Z",
      "fuel": "E",
      "route_id": "764055",
      "track": 4,
      "platform": 3
    },
    {
      "nr": "6154",
      "dest": "Saulkrasti",
      "dep_utc": "2026-04-28T18:15:00Z",
      "fuel": "E",
      "route_id": "764058",
      "track": 11,
      "platform": 1
    },
    {
      "nr": "723",
      "dest": "Liepāja",
      "dep_utc": "2026-04-28T18:20:00Z",
      "fuel": "D",
      "route_id": "764059",
      "track": 1,
      "platform": 2
    },
    {
      "nr": "6527",
      "dest": "Tukums 1",
      "dep_utc": "2026-04-28T18:30:00Z",
      "fuel": "E",
      "route_id": "764062",
      "track": 3,
      "platform": 3
    },
    {
      "nr": "6741",
      "dest": "Jelgava",
      "dep_utc": "2026-04-28T18:35:00Z",
      "fuel": "E",
      "route_id": "764064",
      "track": 5,
      "platform": 4
    },
    {
      "nr": "876",
      "dest": "Valga",
      "dep_utc": "2026-04-28T18:37:00Z",
      "fuel": "D",
      "route_id": "764066",
      "track": 12,
      "platform": 1
    },
    {
      "nr": "6254",
      "dest": "Aizkraukle",
      "dep_utc": "2026-04-28T18:39:00Z",
      "fuel": "E",
      "route_id": "764067",
      "track": 4,
      "platform": 3
    },
    {
      "nr": "6156",
      "dest": "Skulte",
      "dep_utc": "2026-04-28T18:45:00Z",
      "fuel": "E",
      "route_id": "764069",
      "track": 10,
      "platform": 2
    },
    {
      "nr": "6329",
      "dest": "Zolitūde",
      "dep_utc": "2026-04-28T19:00:00Z",
      "fuel": "E",
      "route_id": "764073",
      "track": 3,
      "platform": 3
    },
    {
      "nr": "816",
      "dest": "Madona",
      "dep_utc": "2026-04-28T19:01:00Z",
      "fuel": "D",
      "route_id": "764075",
      "track": 11,
      "platform": 1
    },
    {
      "nr": "6256",
      "dest": "Lielvārde",
      "dep_utc": "2026-04-28T19:09:00Z",
      "fuel": "E",
      "route_id": "764077",
      "track": 4,
      "platform": 3
    },
    {
      "nr": "6158",
      "dest": "Saulkrasti",
      "dep_utc": "2026-04-28T19:15:00Z",
      "fuel": "E",
      "route_id": "764079",
      "track": 10,
      "platform": 2
    },
    {
      "nr": "866",
      "dest": "Valmiera",
      "dep_utc": "2026-04-28T19:30:00Z",
      "fuel": "D",
      "route_id": "764081",
      "track": 11,
      "platform": 1
    },
    {
      "nr": "6529",
      "dest": "Tukums 1",
      "dep_utc": "2026-04-28T19:30:00Z",
      "fuel": "E",
      "route_id": "764082",
      "track": 3,
      "platform": 3
    },
    {
      "nr": "6745",
      "dest": "Jelgava",
      "dep_utc": "2026-04-28T19:35:00Z",
      "fuel": "E",
      "route_id": "764084",
      "track": 5,
      "platform": 4
    },
    {
      "nr": "6258",
      "dest": "Lielvārde",
      "dep_utc": "2026-04-28T19:39:00Z",
      "fuel": "E",
      "route_id": "764085",
      "track": 4,
      "platform": 3
    },
    {
      "nr": "6160",
      "dest": "Skulte",
      "dep_utc": "2026-04-28T19:45:00Z",
      "fuel": "E",
      "route_id": "764088",
      "track": 10,
      "platform": 2
    },
    {
      "nr": "6331",
      "dest": "Zolitūde",
      "dep_utc": "2026-04-28T20:00:00Z",
      "fuel": "E",
      "route_id": "764092",
      "track": 3,
      "platform": 3
    },
    {
      "nr": "6260",
      "dest": "Aizkraukle",
      "dep_utc": "2026-04-28T20:09:00Z",
      "fuel": "E",
      "route_id": "764096",
      "track": 4,
      "platform": 3
    },
    {
      "nr": "6162",
      "dest": "Saulkrasti",
      "dep_utc": "2026-04-28T20:19:00Z",
      "fuel": "E",
      "route_id": "764097",
      "track": 11,
      "platform": 1
    },
    {
      "nr": "6531",
      "dest": "Tukums 1",
      "dep_utc": "2026-04-28T20:30:00Z",
      "fuel": "E",
      "route_id": "764099",
      "track": 3,
      "platform": 3
    },
    {
      "nr": "6747",
      "dest": "Jelgava",
      "dep_utc": "2026-04-28T20:35:00Z",
      "fuel": "E",
      "route_id": "764101",
      "track": 5,
      "platform": 4
    },
    {
      "nr": "846",
      "dest": "Sigulda",
      "dep_utc": "2026-04-28T20:37:00Z",
      "fuel": "D",
      "route_id": "764102",
      "track": 10,
      "platform": 2
    },
    {
      "nr": "6262",
      "dest": "Lielvārde",
      "dep_utc": "2026-04-28T20:39:00Z",
      "fuel": "E",
      "route_id": "764103",
      "track": 4,
      "platform": 3
    },
    {
      "nr": "6164",
      "dest": "Skulte",
      "dep_utc": "2026-04-28T20:47:00Z",
      "fuel": "E",
      "route_id": "764106",
      "track": 11,
      "platform": 1
    },
    {
      "nr": "6333",
      "dest": "Zolitūde",
      "dep_utc": "2026-04-28T21:00:00Z",
      "fuel": "E",
      "route_id": "764110",
      "track": 3,
      "platform": 3
    },
    {
      "nr": "822",
      "dest": "Daugavpils",
      "dep_utc": "2026-04-28T21:01:00Z",
      "fuel": "D",
      "route_id": "764112",
      "track": 1,
      "platform": 2
    },
    {
      "nr": "6264",
      "dest": "Lielvārde",
      "dep_utc": "2026-04-28T21:09:00Z",
      "fuel": "E",
      "route_id": "764113",
      "track": 4,
      "platform": 3
    },
    {
      "nr": "6533",
      "dest": "Tukums 2",
      "dep_utc": "2026-04-28T21:30:00Z",
      "fuel": "E",
      "route_id": "764116",
      "track": 3,
      "platform": 3
    },
    {
      "nr": "848",
      "dest": "Cēsis",
      "dep_utc": "2026-04-28T21:30:00Z",
      "fuel": "D",
      "route_id": "764117",
      "track": 1,
      "platform": 2
    },
    {
      "nr": "6749",
      "dest": "Jelgava",
      "dep_utc": "2026-04-28T21:35:00Z",
      "fuel": "E",
      "route_id": "764118",
      "track": 5,
      "platform": 4
    },
    {
      "nr": "6266",
      "dest": "Aizkraukle",
      "dep_utc": "2026-04-28T21:39:00Z",
      "fuel": "E",
      "route_id": "764119",
      "track": 4,
      "platform": 3
    },
    {
      "nr": "6166",
      "dest": "Skulte",
      "dep_utc": "2026-04-28T21:45:00Z",
      "fuel": "E",
      "route_id": "764122",
      "track": 11,
      "platform": 1
    },
    {
      "nr": "6335",
      "dest": "Zolitūde",
      "dep_utc": "2026-04-28T22:00:00Z",
      "fuel": "E",
      "route_id": "764126",
      "track": 3,
      "platform": 3
    },
    {
      "nr": "6535",
      "dest": "Tukums 2",
      "dep_utc": "2026-04-28T22:30:00Z",
      "fuel": "E",
      "route_id": "764130",
      "track": 3,
      "platform": 3
    },
    {
      "nr": "850",
      "dest": "Sigulda",
      "dep_utc": "2026-04-28T22:30:00Z",
      "fuel": "D",
      "route_id": "764131",
      "track": 10,
      "platform": 2
    },
    {
      "nr": "6751",
      "dest": "Jelgava",
      "dep_utc": "2026-04-28T22:35:00Z",
      "fuel": "E",
      "route_id": "764132",
      "track": 5,
      "platform": 4
    },
    {
      "nr": "6268",
      "dest": "Aizkraukle",
      "dep_utc": "2026-04-28T22:39:00Z",
      "fuel": "E",
      "route_id": "764133",
      "track": 4,
      "platform": 3
    },
    {
      "nr": "6168",
      "dest": "Skulte",
      "dep_utc": "2026-04-28T22:45:00Z",
      "fuel": "E",
      "route_id": "764135",
      "track": 1,
      "platform": 2
    },
    {
      "nr": "6337",
      "dest": "Zolitūde",
      "dep_utc": "2026-04-28T23:00:00Z",
      "fuel": "E",
      "route_id": "764136",
      "track": 3,
      "platform": 3
    },
    {
      "nr": "6753",
      "dest": "Jelgava",
      "dep_utc": "2026-04-28T23:35:00Z",
      "fuel": "E",
      "route_id": "764139",
      "track": 5,
      "platform": 4
    },
    {
      "nr": "6270",
      "dest": "Lielvārde",
      "dep_utc": "2026-04-28T23:39:00Z",
      "fuel": "E",
      "route_id": "764140",
      "track": 4,
      "platform": 3
    },
    {
      "nr": "6170",
      "dest": "Skulte",
      "dep_utc": "2026-04-28T23:45:00Z",
      "fuel": "E",
      "route_id": "764141",
      "track": 10,
      "platform": 2
    },
    {
      "nr": "6537",
      "dest": "Tukums 2",
      "dep_utc": "2026-04-28T23:45:00Z",
      "fuel": "E",
      "route_id": "764142",
      "track": 3,
      "platform": 3
    }
  ]
}