{
  "updated_utc": "2026-05-02T05:58:55Z",
  "updated": "02.05.2026 08:58:55",
  "delays": {
    "765199": {
      "gps_delay_min": 0,
      "stopped": false,
      "gps_active": true
    },
    "765223": {
      "gps_delay_min": 0,
      "stopped": false,
      "gps_active": true
    },
    "765228": {
      "gps_delay_min": 0,
      "stopped": false,
      "gps_active": true
    },
    "765231": {
      "gps_delay_min": 0,
      "stopped": false,
      "gps_active": true
    },
    "765234": {
      "gps_delay_min": 0,
      "stopped": false,
      "gps_active": true
    },
    "765235": {
      "gps_delay_min": 0,
      "stopped": true,
      "gps_active": true
    },
    "765238": {
      "gps_delay_min": 0,
      "stopped": false,
      "gps_active": true
    },
    "765241": {
      "gps_delay_min": 0,
      "stopped": false,
      "gps_active": false
    },
    "765242": {
      "gps_delay_min": 0,
      "stopped": true,
      "gps_active": true
    },
    "765243": {
      "gps_delay_min": 0,
      "stopped": false,
      "gps_active": true
    },
    "765244": {
      "gps_delay_min": 0,
      "stopped": true,
      "gps_active": true
    },
    "765245": {
      "gps_delay_min": 0,
      "stopped": false,
      "gps_active": true
    },
    "765246": {
      "gps_delay_min": 0,
      "stopped": false,
      "gps_active": false
    },
    "765247": {
      "gps_delay_min": 0,
      "stopped": true,
      "gps_active": true
    },
    "765248": {
      "gps_delay_min": 0,
      "stopped": false,
      "gps_active": true
    },
    "765249": {
      "gps_delay_min": 0,
      "stopped": false,
      "gps_active": true
    },
    "765250": {
      "gps_delay_min": 0,
      "stopped": false,
      "gps_active": true
    },
    "765251": {
      "gps_delay_min": 0,
      "stopped": false,
      "gps_active": false
    },
    "765252": {
      "gps_delay_min": 0,
      "stopped": false,
      "gps_active": false
    },
    "765254": {
      "gps_delay_min": 0,
      "stopped": false,
      "gps_active": true
    },
    "765256": {
      "gps_delay_min": 0,
      "stopped": true,
      "gps_active": true
    },
    "765257": {
      "gps_delay_min": 0,
      "stopped": true,
      "gps_active": true
    }
  },
  "alerts": {}
}