{
  "updated_utc": "2026-04-18T07:38:41Z",
  "updated": "18.04.2026 10:38:41",
  "delays": {
    "760008": {
      "gps_delay_min": 0,
      "stopped": true,
      "gps_active": true
    },
    "760013": {
      "gps_delay_min": 0,
      "stopped": false,
      "gps_active": true
    },
    "760018": {
      "gps_delay_min": 0,
      "stopped": false,
      "gps_active": true
    },
    "760028": {
      "gps_delay_min": 0,
      "stopped": false,
      "gps_active": true
    },
    "760030": {
      "gps_delay_min": 0,
      "stopped": true,
      "gps_active": false
    },
    "760031": {
      "gps_delay_min": 0,
      "stopped": false,
      "gps_active": true
    },
    "760034": {
      "gps_delay_min": 0,
      "stopped": false,
      "gps_active": true
    },
    "760035": {
      "gps_delay_min": 0,
      "stopped": false,
      "gps_active": true
    },
    "760036": {
      "gps_delay_min": 0,
      "stopped": false,
      "gps_active": true
    },
    "760037": {
      "gps_delay_min": 0,
      "stopped": false,
      "gps_active": true
    },
    "760038": {
      "gps_delay_min": 0,
      "stopped": false,
      "gps_active": true
    },
    "760039": {
      "gps_delay_min": 0,
      "stopped": false,
      "gps_active": true
    },
    "760040": {
      "gps_delay_min": 0,
      "stopped": false,
      "gps_active": true
    },
    "760041": {
      "gps_delay_min": 0,
      "stopped": false,
      "gps_active": true
    },
    "760042": {
      "gps_delay_min": 0,
      "stopped": false,
      "gps_active": false
    },
    "760043": {
      "gps_delay_min": 0,
      "stopped": false,
      "gps_active": false
    },
    "760044": {
      "gps_delay_min": 0,
      "stopped": true,
      "gps_active": true
    },
    "760045": {
      "gps_delay_min": 0,
      "stopped": true,
      "gps_active": true
    }
  },
  "alerts": {}
}