{
  "updated_utc": "2026-06-19T11:41:31Z",
  "updated": "19.06.2026 14:41:31",
  "delays": {
    "781775": {
      "gps_delay_min": 0,
      "stopped": false,
      "gps_active": true
    },
    "781786": {
      "gps_delay_min": 0,
      "stopped": true,
      "gps_active": true
    },
    "781793": {
      "gps_delay_min": 0,
      "stopped": false,
      "gps_active": false
    },
    "781800": {
      "gps_delay_min": 0,
      "stopped": false,
      "gps_active": true
    },
    "781804": {
      "gps_delay_min": 0,
      "stopped": false,
      "gps_active": false
    },
    "781805": {
      "gps_delay_min": 0,
      "stopped": false,
      "gps_active": false
    },
    "781808": {
      "gps_delay_min": 0,
      "stopped": true,
      "gps_active": true
    },
    "781810": {
      "gps_delay_min": 0,
      "stopped": false,
      "gps_active": false
    },
    "781811": {
      "gps_delay_min": 0,
      "stopped": false,
      "gps_active": false
    },
    "781812": {
      "gps_delay_min": 0,
      "stopped": false,
      "gps_active": true
    },
    "781813": {
      "gps_delay_min": 0,
      "stopped": true,
      "gps_active": true
    },
    "781814": {
      "gps_delay_min": 0,
      "stopped": false,
      "gps_active": false
    },
    "781815": {
      "gps_delay_min": 0,
      "stopped": false,
      "gps_active": false
    },
    "781816": {
      "gps_delay_min": 0,
      "stopped": false,
      "gps_active": true
    },
    "781817": {
      "gps_delay_min": 0,
      "stopped": false,
      "gps_active": false
    },
    "781818": {
      "gps_delay_min": 0,
      "stopped": true,
      "gps_active": true
    },
    "781819": {
      "gps_delay_min": 0,
      "stopped": false,
      "gps_active": false
    },
    "781820": {
      "gps_delay_min": 0,
      "stopped": false,
      "gps_active": true
    },
    "781821": {
      "gps_delay_min": 0,
      "stopped": false,
      "gps_active": false
    },
    "781822": {
      "gps_delay_min": 0,
      "stopped": false,
      "gps_active": false
    },
    "781823": {
      "gps_delay_min": 0,
      "stopped": true,
      "gps_active": true
    },
    "781824": {
      "gps_delay_min": 0,
      "stopped": true,
      "gps_active": true
    },
    "781825": {
      "gps_delay_min": 0,
      "stopped": false,
      "gps_active": false
    },
    "781826": {
      "gps_delay_min": 0,
      "stopped": false,
      "gps_active": true
    },
    "781827": {
      "gps_delay_min": 0,
      "stopped": false,
      "gps_active": false
    },
    "781829": {
      "gps_delay_min": 0,
      "stopped": false,
      "gps_active": false
    }
  },
  "alerts": {}
}