{
  "updated_utc": "2026-04-21T19:50:59Z",
  "updated": "21.04.2026 22:50:59",
  "delays": {
    "761747": {
      "gps_delay_min": 0,
      "stopped": false,
      "gps_active": true
    },
    "761751": {
      "gps_delay_min": 0,
      "stopped": false,
      "gps_active": false
    },
    "761752": {
      "gps_delay_min": 0,
      "stopped": false,
      "gps_active": true
    },
    "761754": {
      "gps_delay_min": 0,
      "stopped": false,
      "gps_active": true
    },
    "761756": {
      "gps_delay_min": 0,
      "stopped": true,
      "gps_active": true
    },
    "761757": {
      "gps_delay_min": 0,
      "stopped": false,
      "gps_active": true
    },
    "761759": {
      "gps_delay_min": 0,
      "stopped": false,
      "gps_active": false
    },
    "761760": {
      "gps_delay_min": 0,
      "stopped": false,
      "gps_active": true
    },
    "761762": {
      "gps_delay_min": 0,
      "stopped": false,
      "gps_active": true
    },
    "761763": {
      "gps_delay_min": 0,
      "stopped": true,
      "gps_active": true
    },
    "761764": {
      "gps_delay_min": 0,
      "stopped": true,
      "gps_active": true
    },
    "761765": {
      "gps_delay_min": 0,
      "stopped": false,
      "gps_active": false
    },
    "761766": {
      "gps_delay_min": 0,
      "stopped": false,
      "gps_active": false
    },
    "761767": {
      "gps_delay_min": 0,
      "stopped": false,
      "gps_active": false
    },
    "761768": {
      "gps_delay_min": 0,
      "stopped": false,
      "gps_active": true
    },
    "761769": {
      "gps_delay_min": 0,
      "stopped": false,
      "gps_active": true
    },
    "761770": {
      "gps_delay_min": 0,
      "stopped": false,
      "gps_active": true
    }
  },
  "alerts": {}
}