{
  "updated_utc": "2026-06-19T03:16:34Z",
  "updated": "19.06.2026 06:16:34",
  "delays": {
    "781634": {
      "gps_delay_min": 0,
      "stopped": false,
      "gps_active": false
    },
    "781635": {
      "gps_delay_min": 0,
      "stopped": false,
      "gps_active": false
    },
    "781641": {
      "gps_delay_min": 0,
      "stopped": false,
      "gps_active": true
    },
    "781642": {
      "gps_delay_min": 0,
      "stopped": false,
      "gps_active": true
    },
    "781643": {
      "gps_delay_min": 0,
      "stopped": true,
      "gps_active": true
    },
    "781644": {
      "gps_delay_min": 0,
      "stopped": false,
      "gps_active": true
    },
    "781645": {
      "gps_delay_min": 0,
      "stopped": false,
      "gps_active": true
    },
    "781646": {
      "gps_delay_min": 0,
      "stopped": false,
      "gps_active": false
    },
    "781647": {
      "gps_delay_min": 0,
      "stopped": false,
      "gps_active": false
    },
    "781648": {
      "gps_delay_min": 0,
      "stopped": true,
      "gps_active": true
    },
    "781649": {
      "gps_delay_min": 0,
      "stopped": false,
      "gps_active": false
    },
    "781650": {
      "gps_delay_min": 0,
      "stopped": false,
      "gps_active": true
    },
    "781651": {
      "gps_delay_min": 0,
      "stopped": false,
      "gps_active": true
    },
    "781652": {
      "gps_delay_min": 0,
      "stopped": false,
      "gps_active": false
    },
    "781653": {
      "gps_delay_min": 0,
      "stopped": false,
      "gps_active": true
    },
    "781654": {
      "gps_delay_min": 0,
      "stopped": false,
      "gps_active": true
    },
    "781655": {
      "gps_delay_min": 0,
      "stopped": true,
      "gps_active": true
    },
    "781656": {
      "gps_delay_min": 0,
      "stopped": false,
      "gps_active": true
    },
    "781657": {
      "gps_delay_min": 0,
      "stopped": false,
      "gps_active": false
    },
    "781658": {
      "gps_delay_min": 0,
      "stopped": false,
      "gps_active": false
    },
    "781659": {
      "gps_delay_min": 0,
      "stopped": true,
      "gps_active": true
    },
    "781660": {
      "gps_delay_min": 0,
      "stopped": false,
      "gps_active": false
    },
    "781661": {
      "gps_delay_min": 0,
      "stopped": false,
      "gps_active": true
    },
    "781662": {
      "gps_delay_min": 0,
      "stopped": true,
      "gps_active": true
    },
    "781663": {
      "gps_delay_min": 0,
      "stopped": false,
      "gps_active": true
    },
    "781664": {
      "gps_delay_min": 0,
      "stopped": false,
      "gps_active": true
    },
    "781665": {
      "gps_delay_min": 0,
      "stopped": true,
      "gps_active": true
    }
  },
  "alerts": {}
}