{
  "updated_utc": "2026-05-18T17:15:46Z",
  "updated": "18.05.2026 20:15:46",
  "delays": {
    "770782": {
      "gps_delay_min": 0,
      "stopped": false,
      "gps_active": true
    },
    "770806": {
      "gps_delay_min": 0,
      "stopped": false,
      "gps_active": true
    },
    "770811": {
      "gps_delay_min": 0,
      "stopped": false,
      "gps_active": false
    },
    "770813": {
      "gps_delay_min": 0,
      "stopped": false,
      "gps_active": false
    },
    "770820": {
      "gps_delay_min": 0,
      "stopped": false,
      "gps_active": true
    },
    "770823": {
      "gps_delay_min": 0,
      "stopped": false,
      "gps_active": true
    },
    "770829": {
      "gps_delay_min": 0,
      "stopped": true,
      "gps_active": true
    },
    "770832": {
      "gps_delay_min": 0,
      "stopped": false,
      "gps_active": false
    },
    "770833": {
      "gps_delay_min": 0,
      "stopped": false,
      "gps_active": true
    },
    "770834": {
      "gps_delay_min": 0,
      "stopped": true,
      "gps_active": true
    },
    "770835": {
      "gps_delay_min": 0,
      "stopped": false,
      "gps_active": true
    },
    "770836": {
      "gps_delay_min": 0,
      "stopped": true,
      "gps_active": true
    },
    "770837": {
      "gps_delay_min": 0,
      "stopped": false,
      "gps_active": false
    },
    "770838": {
      "gps_delay_min": 0,
      "stopped": false,
      "gps_active": true
    },
    "770839": {
      "gps_delay_min": 0,
      "stopped": true,
      "gps_active": true
    },
    "770840": {
      "gps_delay_min": 0,
      "stopped": true,
      "gps_active": true
    },
    "770841": {
      "gps_delay_min": 0,
      "stopped": false,
      "gps_active": true
    },
    "770842": {
      "gps_delay_min": 0,
      "stopped": false,
      "gps_active": false
    },
    "770845": {
      "gps_delay_min": 0,
      "stopped": false,
      "gps_active": true
    },
    "770848": {
      "gps_delay_min": 0,
      "stopped": false,
      "gps_active": true
    },
    "770849": {
      "gps_delay_min": 0,
      "stopped": true,
      "gps_active": true
    },
    "770850": {
      "gps_delay_min": 0,
      "stopped": true,
      "gps_active": true
    }
  },
  "alerts": {}
}