{
  "updated_utc": "2026-06-18T05:38:29Z",
  "updated": "18.06.2026 08:38:29",
  "delays": {
    "781295": {
      "gps_delay_min": 0,
      "stopped": false,
      "gps_active": true
    },
    "781309": {
      "gps_delay_min": 0,
      "stopped": true,
      "gps_active": true
    },
    "781321": {
      "gps_delay_min": 0,
      "stopped": false,
      "gps_active": true
    },
    "781324": {
      "gps_delay_min": 0,
      "stopped": true,
      "gps_active": true
    },
    "781331": {
      "gps_delay_min": 0,
      "stopped": false,
      "gps_active": false
    },
    "781333": {
      "gps_delay_min": 0,
      "stopped": false,
      "gps_active": false
    },
    "781337": {
      "gps_delay_min": 0,
      "stopped": false,
      "gps_active": true
    },
    "781340": {
      "gps_delay_min": 0,
      "stopped": true,
      "gps_active": true
    },
    "781342": {
      "gps_delay_min": 0,
      "stopped": true,
      "gps_active": false
    },
    "781343": {
      "gps_delay_min": 0,
      "stopped": false,
      "gps_active": false
    },
    "781344": {
      "gps_delay_min": 0,
      "stopped": true,
      "gps_active": true
    },
    "781345": {
      "gps_delay_min": 0,
      "stopped": false,
      "gps_active": true
    },
    "781346": {
      "gps_delay_min": 0,
      "stopped": false,
      "gps_active": true
    },
    "781347": {
      "gps_delay_min": 0,
      "stopped": false,
      "gps_active": false
    },
    "781348": {
      "gps_delay_min": 0,
      "stopped": false,
      "gps_active": true
    },
    "781349": {
      "gps_delay_min": 0,
      "stopped": false,
      "gps_active": false
    },
    "781350": {
      "gps_delay_min": 0,
      "stopped": true,
      "gps_active": true
    },
    "781351": {
      "gps_delay_min": 0,
      "stopped": false,
      "gps_active": true
    },
    "781352": {
      "gps_delay_min": 0,
      "stopped": false,
      "gps_active": false
    },
    "781353": {
      "gps_delay_min": 0,
      "stopped": false,
      "gps_active": true
    },
    "781354": {
      "gps_delay_min": 0,
      "stopped": false,
      "gps_active": false
    },
    "781355": {
      "gps_delay_min": 0,
      "stopped": false,
      "gps_active": true
    },
    "781356": {
      "gps_delay_min": 0,
      "stopped": true,
      "gps_active": true
    },
    "781357": {
      "gps_delay_min": 0,
      "stopped": false,
      "gps_active": false
    },
    "781358": {
      "gps_delay_min": 0,
      "stopped": true,
      "gps_active": true
    },
    "781359": {
      "gps_delay_min": 0,
      "stopped": false,
      "gps_active": true
    },
    "781360": {
      "gps_delay_min": 0,
      "stopped": true,
      "gps_active": true
    },
    "781361": {
      "gps_delay_min": 0,
      "stopped": true,
      "gps_active": true
    },
    "781362": {
      "gps_delay_min": 0,
      "stopped": true,
      "gps_active": true
    }
  },
  "alerts": {}
}