{
  "updated_utc": "2026-04-18T04:57:27Z",
  "updated": "18.04.2026 07:57:27",
  "delays": {
    "759962": {
      "gps_delay_min": 0,
      "stopped": false,
      "gps_active": false
    },
    "759968": {
      "gps_delay_min": 0,
      "stopped": false,
      "gps_active": false
    },
    "759975": {
      "gps_delay_min": 0,
      "stopped": false,
      "gps_active": true
    },
    "759987": {
      "gps_delay_min": 0,
      "stopped": true,
      "gps_active": true
    },
    "759988": {
      "gps_delay_min": 0,
      "stopped": false,
      "gps_active": false
    },
    "759993": {
      "gps_delay_min": 0,
      "stopped": false,
      "gps_active": true
    },
    "759995": {
      "gps_delay_min": 0,
      "stopped": false,
      "gps_active": true
    },
    "759997": {
      "gps_delay_min": 0,
      "stopped": false,
      "gps_active": true
    },
    "759998": {
      "gps_delay_min": 0,
      "stopped": false,
      "gps_active": true
    },
    "759999": {
      "gps_delay_min": 0,
      "stopped": true,
      "gps_active": false
    },
    "760000": {
      "gps_delay_min": 0,
      "stopped": true,
      "gps_active": false
    },
    "760001": {
      "gps_delay_min": 0,
      "stopped": true,
      "gps_active": true
    },
    "760002": {
      "gps_delay_min": 0,
      "stopped": false,
      "gps_active": false
    },
    "760003": {
      "gps_delay_min": 0,
      "stopped": false,
      "gps_active": true
    },
    "760004": {
      "gps_delay_min": 0,
      "stopped": false,
      "gps_active": false
    },
    "760005": {
      "gps_delay_min": 0,
      "stopped": false,
      "gps_active": false
    },
    "760006": {
      "gps_delay_min": 0,
      "stopped": false,
      "gps_active": false
    },
    "760007": {
      "gps_delay_min": 0,
      "stopped": false,
      "gps_active": false
    },
    "760008": {
      "gps_delay_min": 0,
      "stopped": true,
      "gps_active": true
    },
    "760009": {
      "gps_delay_min": 0,
      "stopped": false,
      "gps_active": false
    },
    "760011": {
      "gps_delay_min": 0,
      "stopped": false,
      "gps_active": true
    },
    "760705": {
      "gps_delay_min": 0,
      "stopped": false,
      "gps_active": true
    },
    "760707": {
      "gps_delay_min": 0,
      "stopped": false,
      "gps_active": false
    },
    "760708": {
      "gps_delay_min": 0,
      "stopped": false,
      "gps_active": false
    }
  },
  "alerts": {}
}