{
  "updated_utc": "2026-06-18T19:58:28Z",
  "updated": "18.06.2026 22:58:28",
  "delays": {
    "781603": {
      "gps_delay_min": 0,
      "stopped": true,
      "gps_active": false
    },
    "781609": {
      "gps_delay_min": 0,
      "stopped": false,
      "gps_active": false
    },
    "781615": {
      "gps_delay_min": 0,
      "stopped": false,
      "gps_active": true
    },
    "781616": {
      "gps_delay_min": 0,
      "stopped": false,
      "gps_active": false
    },
    "781617": {
      "gps_delay_min": 0,
      "stopped": true,
      "gps_active": true
    },
    "781618": {
      "gps_delay_min": 0,
      "stopped": false,
      "gps_active": false
    },
    "781619": {
      "gps_delay_min": 0,
      "stopped": false,
      "gps_active": false
    },
    "781620": {
      "gps_delay_min": 0,
      "stopped": false,
      "gps_active": true
    },
    "781621": {
      "gps_delay_min": 0,
      "stopped": true,
      "gps_active": true
    },
    "781622": {
      "gps_delay_min": 0,
      "stopped": false,
      "gps_active": false
    },
    "781623": {
      "gps_delay_min": 0,
      "stopped": false,
      "gps_active": true
    },
    "781624": {
      "gps_delay_min": 0,
      "stopped": true,
      "gps_active": true
    },
    "781625": {
      "gps_delay_min": 0,
      "stopped": false,
      "gps_active": false
    },
    "781626": {
      "gps_delay_min": 0,
      "stopped": false,
      "gps_active": false
    },
    "781627": {
      "gps_delay_min": 0,
      "stopped": true,
      "gps_active": true
    }
  },
  "alerts": {}
}